setup.cfg
setup.py
dist_alx_Arsen/Binomialdistribution.py
dist_alx_Arsen/Gaussiandistribution.py
dist_alx_Arsen/Generaldistribution.py
dist_alx_Arsen/__init__.py
dist_alx_Arsen.egg-info/PKG-INFO
dist_alx_Arsen.egg-info/SOURCES.txt
dist_alx_Arsen.egg-info/dependency_links.txt
dist_alx_Arsen.egg-info/not-zip-safe
dist_alx_Arsen.egg-info/top_level.txt