Metadata-Version: 2.1
Name: dist-alx-Arsen
Version: 0.0
Summary: Gaussian and Binomial distributions
Home-page: UNKNOWN
Author-email: rasen13@mail.ru
License: UNKNOWN
Platform: UNKNOWN
